Lab02_IA/__init__.py
Lab02_IA/cli.py
Lab02_IA-1.0.0.dist-info/METADATA
Lab02_IA-1.0.0.dist-info/WHEEL
Lab02_IA-1.0.0.dist-info/entry_points.txt
Lab02_IA-1.0.0.dist-info/top_level.txt
Lab02_IA-1.0.0.dist-info/RECORD
