Metadata-Version: 2.1
Name: Lab02-IA
Version: 1.0.0
Home-page: https://github.com/dele20361/Lab02-IA
Author: Gabriela Contreras
Requires: pgmpy
Requires-Python: >=3.6
